[
  {
    "title": "Certificate Integer Gen 4",
    "description": "this is my certificate when I took part in the national tkj pocket tracker competition held by UPG / ganesha education university.",
    "technology": "Networking",
    "image": "../certificate/tegar-dito-priandika-integer-4.webp",
    "link": "https://omtegar.vercel.app/certificate/tegar-dito-priandika-integer-4.webp",
    "repo": "#"
  },
  {
    "title": "Certificate Telkom Indonesia",
    "description": "my first certificate hehe, a certification test or level increase held by the Telkom Indonesia educational foundation.",
    "technology": "Networking",
    "image": "../certificate/SERTIFIKAT-UKL-X-A30-2021_2022-Tegar-Dito-Priandika.webp",
    "link": "https://omtegar.vercel.app/certificate/tegar-dito-priandika-integer-4.webp",
    "repo" : "#"
  },
  {
    "title": "Certificate Progate CLI",
    "description": "this is a command line study completion certificate from progate",
    "technology": "Programing",
    "image": "../certificate/command-line-progate.webp",
    "link": "https://omtegar.vercel.app/certificate/command-line-progate.webp",
    "repo" : "#"
  }
]
